sudokustepper/__init__.py
sudokustepper/__main__.py
sudokustepper/grid.py
sudokustepper/gui.py
sudokustepper/resources.py
sudokustepper/solvers.py
sudokustepper-0.2.3.dist-info/LICENSE
sudokustepper-0.2.3.dist-info/METADATA
sudokustepper-0.2.3.dist-info/WHEEL
sudokustepper-0.2.3.dist-info/entry_points.txt
sudokustepper-0.2.3.dist-info/top_level.txt
sudokustepper-0.2.3.dist-info/RECORD
